eta_nexus/__init__.py
eta_nexus/connection_manager.py
eta_nexus/connections/__init__.py
eta_nexus/connections/connection.py
eta_nexus/connections/connection_utils.py
eta_nexus/connections/emonio_connection.py
eta_nexus/connections/eneffco_connection.py
eta_nexus/connections/entsoe_connection.py
eta_nexus/connections/forecastsolar_connection.py
eta_nexus/connections/modbus_connection.py
eta_nexus/connections/opcua_connection.py
eta_nexus/connections/wetterdienst_connection.py
eta_nexus/nodes/__init__.py
eta_nexus/nodes/emonio_node.py
eta_nexus/nodes/eneffco_node.py
eta_nexus/nodes/entsoe_node.py
eta_nexus/nodes/forecastsolar_node.py
eta_nexus/nodes/local_node.py
eta_nexus/nodes/modbus_node.py
eta_nexus/nodes/node.py
eta_nexus/nodes/node_utils.py
eta_nexus/nodes/opcua_node.py
eta_nexus/nodes/wetterdienst_node.py
eta_nexus/py.typed
eta_nexus/servers/__init__.py
eta_nexus/servers/loaders/__init__.py
eta_nexus/servers/loaders/opcua_server_loader.py
eta_nexus/servers/modbus_server.py
eta_nexus/servers/opcua_server.py
eta_nexus/subhandlers/__init__.py
eta_nexus/subhandlers/csv_subhandler.py
eta_nexus/subhandlers/df_subhandler.py
eta_nexus/subhandlers/multi_subhandler.py
eta_nexus/subhandlers/subhandler.py
eta_nexus/timeseries/__init__.py
eta_nexus/timeseries/dataframes.py
eta_nexus/util/__init__.py
eta_nexus/util/auth_utils.py
eta_nexus/util/io_utils.py
eta_nexus/util/logging_utils.py
eta_nexus/util/time_utils.py
eta_nexus/util/type_annotations.py
eta_nexus/util/utils.py
examples/__init__.py
examples/connections/__init__.py
examples/connections/read_emonio.py
examples/connections/read_series_eneffco.py
examples/connections/read_series_entsoe.py
examples/connections/read_series_forecastsolar.py
examples/connections/read_series_wetterdienst.py
examples/forecasting/__init__.py
examples/forecasting/main.py
examples/forecasting/resources/emag_gt_forecast.onnx
eta_nexus-0.1.1.dist-info/AUTHORS.rst
eta_nexus-0.1.1.dist-info/LICENSE
eta_nexus-0.1.1.dist-info/METADATA
eta_nexus-0.1.1.dist-info/WHEEL
eta_nexus-0.1.1.dist-info/RECORD
