Metadata-Version: 2.3
Name: eta-nexus
Version: 0.1.1
Summary: Provides a standardized way to connect to machines and devices in a factory or other factory systems
License: BSD-2-Clause
Keywords: connectivity,servers,iot,multi-protocol,eta-fabrik
Author: Technical University of Darmstadt, Institute for Production Management, Technology and Machine Tools (PTW)
Author-email: info@ptw.tu-darmstadt.de
Maintainer: Andreas Clement
Maintainer-email: A.Clement@PTW.TU-Darmstadt.de
Requires-Python: >=3.10.16, <3.12.0
Classifier: Development Status :: 4 - Beta
Classifier: Intended Audience :: Developers
Classifier: Intended Audience :: Education
Classifier: Intended Audience :: Manufacturing
Classifier: Intended Audience :: Science/Research
Classifier: License :: OSI Approved :: BSD License
Classifier: Operating System :: OS Independent
Classifier: Programming Language :: Python :: 3
Classifier: Programming Language :: Python :: 3.11
Classifier: Topic :: Scientific/Engineering :: Interface Engine/Protocol Translator
Classifier: Topic :: Software Development :: Libraries :: Python Modules
Provides-Extra: docs
Provides-Extra: examples
Requires-Dist: asyncua-fork-for-eta-utility (==1.0.7)
Requires-Dist: attrs (>=23.1.0,<24.0.0)
Requires-Dist: cryptography (>=41.0.4,<42.0.0)
Requires-Dist: esbonio (>=0.16.5,<0.17.0) ; extra == "docs"
Requires-Dist: numpy (>=1.26.0,<2.0.0)
Requires-Dist: onnxruntime (>=1.21.0) ; extra == "examples"
Requires-Dist: pandas[excel,xml] (>=2.2.2,<2.3.0)
Requires-Dist: pymodbustcp (>=0.2.0,<0.4.0)
Requires-Dist: python-dateutil (>=2.8.2,<3.0.0)
Requires-Dist: python-dotenv (>=1.0.1,<2.0.0)
Requires-Dist: pyyaml (>=6.0.2,<7.0.0)
Requires-Dist: requests (>=2.31.0,<3.0.0)
Requires-Dist: requests-cache (>=1.2.0,<2.0.0)
Requires-Dist: sphinx (>=8.0.0,<9.0.0) ; extra == "docs"
Requires-Dist: sphinx-copybutton (>=0.5.2,<0.6.0) ; extra == "docs"
Requires-Dist: sphinx-rtd-theme (>=3.0.0,<4.0.0) ; extra == "docs"
Requires-Dist: toml (>=0.10.2,<0.11.0)
Requires-Dist: wetterdienst (>=0.88.0,<0.89.0)
Project-URL: Documentation, https://eta-nexus.readthedocs.io/
Project-URL: Homepage, https://www.ptw.tu-darmstadt.de
Project-URL: Repository, https://git.ptw.maschinenbau.tu-darmstadt.de/eta-fabrik/public/eta-nexus
Project-URL: issues, https://git.ptw.maschinenbau.tu-darmstadt.de/eta-fabrik/public/eta-nexus/-/issues
